odevlib/__init__.py
odevlib/admin/__init__.py
odevlib/admin/errors.py
odevlib/admin/omodel.py
odevlib/admin/rbac.py
odevlib/apps.py
odevlib/business_logic/__init__.py
odevlib/business_logic/pagination.py
odevlib/business_logic/rbac/__init__.py
odevlib/business_logic/rbac/permissions.py
odevlib/business_logic/relations.py
odevlib/caching/__init__.py
odevlib/caching/redis_cache.py
odevlib/decorators/__init__.py
odevlib/decorators/error_atomicity.py
odevlib/decorators/rbac.py
odevlib/decorators/transaction.py
odevlib/distributed/__init__.py
odevlib/distributed/message_broker.py
odevlib/drf_spectacular/__init__.py
odevlib/drf_spectacular/ofilter_extension.py
odevlib/errors/__init__.py
odevlib/errors/codes.py
odevlib/exceptions/__init__.py
odevlib/exceptions/immutable.py
odevlib/exceptions/integrity.py
odevlib/fields/__init__.py
odevlib/fields/multiple_value_field.py
odevlib/fields/rbac_model.py
odevlib/filters/__init__.py
odevlib/filters/backends/__init__.py
odevlib/filters/backends/ofilter_backend.py
odevlib/filters/multiple_value_filter.py
odevlib/integrations/__init__.py
odevlib/integrations/odevlib/__init__.py
odevlib/integrations/odevlib/api_client.py
odevlib/middleware/__init__.py
odevlib/middleware/current_user.py
odevlib/middleware/timescale_logger.py
odevlib/migrations/0001_initial_models.py
odevlib/migrations/0002_added_request_logger.py
odevlib/migrations/0003_updated_request_log_entry.py
odevlib/migrations/__init__.py
odevlib/models/__init__.py
odevlib/models/errors.py
odevlib/models/logging.py
odevlib/models/omodel.py
odevlib/models/rbac/__init__.py
odevlib/models/rbac/instance_role_assignment.py
odevlib/models/rbac/mixins.py
odevlib/models/rbac/role.py
odevlib/models/rbac/role_assignment.py
odevlib/models/rbac/role_hierarchy.py
odevlib/models/simple_permission_system.py
odevlib/permissions.py
odevlib/prefetching/__init__.py
odevlib/prefetching/prefetch.py
odevlib/py.typed
odevlib/schema/__init__.py
odevlib/schema/oautoschema.py
odevlib-0.1.4.dist-info/LICENSE
odevlib-0.1.4.dist-info/METADATA
odevlib-0.1.4.dist-info/WHEEL
odevlib-0.1.4.dist-info/RECORD
